{
  "signIn": "Iniciar sesión",
  "signUp": "Registrarse",
  "tools": "Herramientas",
  "contactUs": "Contáctenos",
  "heroTitle": "Editor de PDF en línea todo en uno",
  "heroSubtitle": "Edite, convierta y firme los PDF fácilmente. Es rápido, sencillo y seguro.",
  "dropFileHere": "Suelte su archivo aquí",
  "browseFiles": "Explorar archivos",
  "uploadLimit": "Hasta 100 MB para PDF y hasta 20 MB para DOC, DOCX, PPT, PPTX, XLS, XLSX, BMP, JPG, JPEG, GIF, PNG o TXT",
  "uploadFromGoogleDrive": "Cargar desde Google Drive",
  "uploadFromDropbox": "Cargar desde Dropbox",
  "uploadFromOneDrive": "Cargar desde OneDrive",
  "documentsEdited": "Documentos editados",
  "editingEssentials": "Elementos esenciales de edición",
  "documentsSigned": "Documentos firmados",
  "annotatePdf": "Anotar PDF",
  "annotatePdfDesc": "Resalte y añada texto, imágenes, formas, dibujos, notas adhesivas y más.",
  "editPdf": "Editar PDF",
  "editPdfDesc": "Edite sus PDF quitando, editando o añadiendo texto y cambiando fuentes y colores.",
  "signPdf": "Firmar PDF",
  "signPdfDesc": "Coloque su firma, iniciales, fechas, casillas de verificación y más.",
  "convertDocument": "Convertir documento",
  "convertDocumentDesc": "Convierta fácilmente archivos a PDF, Word y Excel.",
  "mergeDocuments": "Fusionar documentos",
  "mergeDocumentsDesc": "Combine los PDF en cualquier orden con nuestra herramienta de fusión.",
  "compressPdf": "Comprimir PDF",
  "compressPdfDesc": "Reduzca el tamaño y optimice el PDF para obtener la máxima calidad.",
  "redactPdf": "Censurar PDF",
  "redactPdfDesc": "Elimine de forma definitiva la información confidencial de su PDF.",
  "organizePages": "Organizar páginas",
  "organizePagesDesc": "Ordene las páginas de su PDF como desee. Elimine o añada páginas según se requiera.",
  "splitExtractPages": "Dividir y extraer páginas",
  "splitExtractPagesDesc": "Divida y extraiga páginas de un PDF para crear archivos separados.",
  "passwordProtect": "Proteger con contraseña",
  "passwordProtectDesc": "Proteja sus PDF agregando una contraseña.",
  "unlockPdf": "Desbloquear PDF",
  "unlockPdfDesc": "Elimine las contraseñas de los PDF para obtener flexibilidad y acceso total.",
  "addWatermark": "Añadir marca de agua",
  "addWatermarkDesc": "Añada una marca de agua o texto para proteger sus PDF.",
  "rotatePages": "Rotar páginas",
  "rotatePagesDesc": "Rote las páginas de sus PDF a modo vertical u horizontal.",
  "deletePages": "Eliminar páginas",
  "deletePagesDesc": "Elimine una o varias páginas de su PDF.",
  "cropPages": "Recortar páginas",
  "cropPagesDesc": "Recorte sus PDF con nuestra herramienta para recortar.",
  "advantagesTitle": "La solución definitiva para editar y gestionar documentos PDF fácilmente",
  "advantagesSubtitle": "QwerPDF incluye todo lo necesario para editar y administrar documentos PDF!",
  "pdfEditingMadeEasy": "La edición de PDF simplificada",
  "pdfEditingMadeEasyDesc": "Edite sus PDF sin esfuerzo con nuestras intuitivas herramientas. Añada texto, imágenes, anotaciones o firmas electrónicas con solo unos clics.",
  "safeAndSecure": "100% seguro y protegido",
  "safeAndSecureDesc": "QwerPDF protege sus documentos y privacidad. Puede aumentar la seguridad con funciones de cifrado de contraseñas de archivos.",
  "fastAndEasy": "Conversión en línea rápida y sencilla",
  "fastAndEasyDesc": "Convierta rápidamente sus archivos a formatos como Word, PDF, Excel, PNG, JPG y más.",
  "noSoftware": "No requiere instalación de software",
  "noSoftwareDesc": "Con QwerPDF, no son necesarias descargas ni extensiones de navegador. Nuestro editor está totalmente basado en la web.",
  "faqTitle": "Preguntas frecuentes",
  "general": "General",
  "security": "Seguridad",
  "accountBilling": "Cuenta y facturación",
  "bannerTitle": "EDICIÓN DE PDF SIMPLIFICADA",
  "bannerSubtitle": "Todas las herramientas de PDF que necesita en una única plataforma",
  "getStartedFree": "Comenzar gratis",
  "footerTagline": "Soluciones para PDF todo en uno",
  "help": "Ayuda",
  "account": "Cuenta",
  "legal": "Legal",
  "faq": "Preguntas frecuentes",
  "pricing": "Precios",
  "register": "Registrarse",
  "unsubscribe": "Cancelar suscripción",
  "termsAndConditions": "Términos y condiciones",
  "privacyPolicy": "Política de privacidad",
  "allRightsReserved": "QwerPDF | Todos los derechos reservados",
  "securityCompliance": "Seguridad y cumplimiento",
  "plansAndPricing": "Planes y precios",
  "annual": "Anual",
  "monthly": "Mensual",
  "invoicedEveryYear": "Facturado anualmente",
  "invoicedEveryMonth": "Facturado mensualmente",
  "save60": "Ahorre 60%",
  "buyNow": "Comprar ahora",
  "unlimitedAccess": "Acceso ilimitado a funciones premium",
  "contactUsTitle": "Contáctenos",
  "contactUsDesc": "¿Necesita ayuda? Complete el formulario y nuestro equipo se pondrá en contacto lo antes posible.",
  "fullName": "Nombre completo",
  "yourEmailAddress": "Su dirección de correo electrónico",
  "subject": "Asunto",
  "chooseSubject": "Elegir asunto",
  "description": "Descripción",
  "send": "Enviar",
  "notRegisteredYet": "¿Aún no está registrado?",
  "alreadyHaveAccount": "¿Ya tiene una cuenta?",
  "signInWithGoogle": "Iniciar sesión con Google",
  "signInWithFacebook": "Iniciar sesión con Facebook",
  "continueWithGoogle": "Continuar con Google",
  "continueWithFacebook": "Continuar con Facebook",
  "orSignInWithEmail": "O, iniciar sesión con su correo electrónico",
  "orSignUpWithEmail": "O, registrarse con su correo electrónico",
  "enterEmailHere": "Ingrese su correo electrónico aquí",
  "enterPasswordHere": "Ingrese su contraseña aquí",
  "forgotPassword": "¿Olvidó su contraseña?",
  "passwordMinLength": "La contraseña debe tener al menos 4 caracteres",
  "download": "Descargar",
  "saveChanges": "Guardar cambios",
  "properties": "Propiedades",
  "fileName": "Nombre del archivo",
  "fileSize": "Tamaño del archivo",
  "fileType": "Tipo",
  "pdfPreview": "Vista previa del PDF",
  "signOut": "Cerrar sesión",
  "allTools": "Todas las herramientas",
  "allToolsTab": "Todas las herramientas",
  "editAndSignTab": "Editar y firmar",
  "convertTab": "Convertir",
  "organizeTab": "Organizar",
  "securityTab": "Seguridad",
  "coreFeatures": "Funciones principales",
  "allPdfToolsTitle": "Todas las PDF Herramientas que necesita",
  "allPdfToolsSubtitle": "Elija entre nuestro conjunto completo de {count}+ potentes herramientas diseñadas para que sus flujos de trabajo PDF sean fluidos.",
  "comingSoon": "Próximamente",
  "comingSoonShort": "Próximamente",
  "viewAllTools": "Ver todas las herramientas {count}",
  "powerfulTools": "Herramientas poderosas",
  "browseFilesHint": "o haga clic para navegar desde su computadora",
  "uploadErrorFallback": "No se pudo iniciar el editor en este navegador. Pruebe Chrome o desactive la navegación privada.",
  "trustedBy": "Con la confianza de profesionales de empresas líderes a nivel mundial",
  "editingComplete": "Edición completa",
  "encrypted256Bit": "Cifrado de 256 bits",
  "convertedInSeconds": "Convertido en 2 segundos",
  "worksEverywhere": "Funciona en todas partes",
  "sampleDocumentName": "Documento.pdf",
  "sampleDocumentSize": "2,4 MB",
  "filesProtectedTitle": "Sus archivos están protegidos",
  "filesProtectedSubtitle": "Cifrado de extremo a extremo habilitado",
  "sslEncryption": "SSL/TLS cifrado",
  "autoDeleteAfterHour": "Eliminación automática después de 1 hora",
  "noDataStored": "No hay datos almacenados en los servidores",
  "converting": "Convirtiendo...",
  "worksOnAnyDevice": "Funciona en cualquier dispositivo",
  "noDownloadsRequired": "No requiere descargas",
  "desktop": "Escritorio",
  "mobile": "Móvil",
  "tablet": "Tableta",
  "advantagesSubtitleAlt": "Todo lo que necesita para trabajar con archivos PDF, todo en un solo lugar",
  "faqSubtitle": "Encuentre respuestas a preguntas comunes sobre nuestro PDF herramientas",
  "faqWhatIs": "¿Qué es QwerPDF?",
  "faqWhatIsAnswer": "QwerPDF es un editor PDF en línea todo en uno que le permite editar, convertir, firmar y administrar sus documentos PDF de manera fácil y segura. Proporciona más de 50 herramientas para todas sus necesidades de PDF.",
  "faqNoInstall": "¿Necesito descargar o instalar algo para usar QwerPDF?",
  "faqNoInstallAnswer": "No, QwerPDF está completamente basado en web. Puede utilizar todas nuestras herramientas directamente en su navegador sin descargar ningún software ni instalar extensiones del navegador.",
  "faqMerge": "¿Puedo fusionar archivos PDF con QwerPDF?",
  "faqMergeAnswer": "Sí, puede combinar fácilmente varios archivos PDF en un solo documento utilizando nuestra herramienta Combinar documentos. Simplemente cargue sus archivos y combínelos en el orden que prefiera.",
  "faqConvertWord": "¿Puedo convertir un documento de Word en un PDF?",
  "faqConvertWordAnswer": "¡Absolutamente! QwerPDF admite la conversión de varios formatos de archivo, incluidos Word (DOC, DOCX), Excel (XLS, XLSX), PowerPoint (PPT, PPTX) e imágenes al formato PDF.",
  "faqOrganizePages": "¿Cómo agrego, muevo y giro páginas?",
  "faqOrganizePagesAnswer": "Utilice nuestra herramienta Organizar páginas para agregar, mover, eliminar o rotar páginas en sus documentos PDF. Simplemente cargue su PDF y arrastre las páginas para reordenarlas o use los controles de rotación.",
  "faqFreeTools": "¿Por qué ciertos sitios web ofrecen PDF funciones de edición de forma gratuita?",
  "faqFreeToolsAnswer": "Algunos sitios web ofrecen funciones gratuitas limitadas, pero pueden tener restricciones en cuanto al tamaño del archivo, la cantidad de documentos o incluir marcas de agua. QwerPDF proporciona herramientas premium con todas las funciones y sin limitaciones para los suscriptores.",
  "faqSafe": "¿Es seguro usar QwerPDF?",
  "faqSafeAnswer": "Sí, QwerPDF utiliza cifrado y medidas de seguridad estándar de la industria para proteger sus documentos e información personal. Los archivos se eliminan automáticamente después del procesamiento, a menos que elija guardarlos.",
  "guestUsage": "Uso de invitados: {remaining} / {limit} descargas restantes hoy",
  "guestUsageHint": "El procesamiento de PDF permanece en su navegador. Inicie sesión con Google para desbloquear un mayor uso gratuito.",
  "limitedBrowserStorage": "Almacenamiento limitado en el navegador",
  "limitedBrowserStorageDesc": "Su archivo aún se abrirá y procesará normalmente en esta pestaña, pero no podemos guardarlo para más adelante. Esto sucede a menudo en la navegación privada. Si actualiza o cierra esta página, es posible que deba cargar el archivo nuevamente.",
  "continueWhereLeftOff": "Continúa donde lo dejaste",
  "checkingBrowserCache": "Comprobando el caché de tu navegador...",
  "resumeFromCache": "Tu PDF permanece en tu dispositivo. Puede reanudar desde el último archivo que abrió o guardó.",
  "clearCache": "Borrar caché",
  "dropFilesHere": "Soltar archivos aquí",
  "dropzoneConvertSubtitle": "PDF, Office, imágenes o archivos de texto",
  "dropzonePdfSubtitle": "PDF archivo de hasta 100 MB",
  "mergeSelectMultiple": "Seleccione 2 o más archivos PDF",
  "dropzoneSupportedFormats": "Compatible: PDF y formatos comunes",
  "resumeLastSaved": "Reanudar último guardado PDF",
  "resumeLastOpened": "Reanudar último abierto PDF",
  "toolNotImplemented": "Esta herramienta aún no está implementada. Pruebe Anotar, Firmar, Convertir, Fusionar o Comprimir.",
  "chooseAnotherFile": "Elige otro archivo",
  "otherPdfTools": "Otro PDF Herramientas",
  "uploadDocument": "Cargar documento",
  "guestDocMissing": "Este documento ya no está disponible en este dispositivo. Sube un archivo para comenzar de nuevo.",
  "fileTooLarge": "El archivo \"{name}\" ({size}) excede el límite {limit}.",
  "dropzoneSubtitle": "O elige un archivo de tu computadora",
  "dropPdfToCrop": "Coloque un PDF aquí para recortar",
  "dropPdfToCompress": "Coloque un PDF aquí para comprimir",
  "compressSubtitle": "Reduzca el tamaño del archivo PDF manteniendo la calidad",
  "compressing": "Comprimiendo...",
  "compressDownload": "Comprima y descargue",
  "dropPdfToUnlock": "Coloque un PDF aquí para desbloquear",
  "unlockSubtitle": "Quite la protección con contraseña de su PDF",
  "unlocking": "Desbloqueando...",
  "unlockDownload": "Desbloqueo y descarga",
  "dropPdfToProtect": "Coloque un PDF aquí para proteger",
  "protectSubtitle": "Agregue protección con contraseña a su PDF",
  "protecting": "Protegiendo...",
  "protectDownload": "Proteger y descargar",
  "dropPdfToSplit": "Coloque un PDF aquí para dividir/extraer",
  "splitSubtitle": "Dividir PDF en múltiples archivos o extraer páginas específicas",
  "working": "Trabajando...",
  "extractDownload": "Extraer y descargar",
  "splitDownloadZip": "Dividir y descargar ZIP",
  "mergeDownload": "Fusionar y descargar",
  "merging": "Fusionar...",
  "mergeSubtitle": "Combinar archivos en un solo PDF",
  "mergeMinFiles": "Cargue al menos 2 Archivos PDF.",
  "changeFile": "Cambiar archivo",
  "uploadPdfOnly": "Cargue un archivo PDF.",
  "cropDownload": "Recortar y descargar",
  "dropPdfToWatermark": "Coloque un PDF aquí para marcar con agua",
  "watermarkSubtitle": "Agregue una marca de agua de texto a sus documentos PDF",
  "watermarkPreview": "Vista previa de marca de agua",
  "watermarkText": "Texto de marca de agua",
  "applyDownload": "Aplicar y descargar",
  "applySignatureDownload": "Aplicar firma y descargar",
  "signing": "Firmar...",
  "dropPdfToSign": "Coloque un PDF aquí para firmar",
  "signSubtitle": "Agregue su firma a cualquier documento PDF",
  "drawSignature": "Dibuja tu firma",
  "signatureTip": "Consejo: usa el mouse o toca para firmar",
  "signDrawFirst": "Primero dibuje una firma.",
  "signFailed": "Error de firma",
  "page": "Página",
  "widthPt": "Ancho (pt)",
  "rightMargin": "Margen derecho",
  "bottomMargin": "Margen inferior",
  "clear": "Borrar",
  "splitExtractLabel": "Extraer a PDF",
  "splitExtractDesc": "Extraer páginas seleccionadas en una PDF",
  "splitZipLabel": "Dividir a ZIP",
  "splitZipDesc": "Un PDF por página en el archivo ZIP",
  "splitModeLabel": "Modo dividido",
  "pageRangeLabel": "Rango de páginas",
  "pageRangePlaceholder": "p.e. 1-3, 5, 7",
  "pageRangeExamples": "Ejemplos: 1-3, 1,3,5, 2-4,8",
  "pageRangeTotal": "Total: {count} páginas",
  "splitPagesRequired": "Ingrese las páginas para extraer.",
  "splitFailed": "Error de división",
  "pageCount": "{count} páginas",
  "fileCount": "{count} archivo(s)",
  "modeLabel": "Modo",
  "convertModeAuto": "Auto",
  "convertModePdfToImages": "PDF → Imágenes (.zip)",
  "convertModePdfToText": "PDF → Texto (.txt)",
  "convertModeImagesToPdf": "Imágenes → PDF",
  "convertModeFileToPdf": "Oficina → PDF (autohospedado)",
  "formatLabel": "Formato",
  "formatPng": "PNG",
  "formatJpg": "JPG",
  "dpiLabel": "DPI",
  "qualityLabel": "Calidad",
  "convertSingleFileError": "Cargue un solo archivo para la conversión.",
  "convertServiceUnavailable": "El servicio de conversión autohospedado no está disponible",
  "convertFailed": "Error de conversión",
  "passwordLabel": "Contraseña",
  "passwordPlaceholder": "Ingrese la contraseña...",
  "confirmPasswordLabel": "Confirmar contraseña",
  "confirmPasswordPlaceholder": "Confirmar contraseña...",
  "passwordStrengthVeryWeak": "Muy débil",
  "passwordStrengthWeak": "Débil",
  "passwordStrengthFair": "Regular",
  "passwordStrengthGood": "Bueno",
  "passwordStrengthStrong": "Fuerte",
  "passwordRequiredError": "Por favor ingrese una contraseña.",
  "passwordMismatchError": "Las contraseñas no coinciden.",
  "protectFailed": "No se pudo proteger PDF",
  "passwordLocalNote": "Esto se ejecuta localmente en su navegador usando qpdf (WebAssembly). Su contraseña nunca sale de su dispositivo.",
  "unlockFailed": "No se pudo desbloquear PDF",
  "passwordOptionalHint": "(déjelo vacío si no es necesario)",
  "unlockPasswordPlaceholder": "Ingrese PDF contraseña...",
  "unlockRestrictionsHint": "Algunos archivos PDF tienen restricciones sin requerir una contraseña",
  "unlockLegalNotice": "Utilice esta herramienta solo para desbloquear archivos PDF a los que tenga permiso para acceder. El procesamiento ocurre localmente en su navegador.",
  "presetBalanced": "Equilibrado",
  "presetBalancedDesc": "Buena calidad, reducción de tamaño moderada",
  "presetSmaller": "Más pequeño",
  "presetSmallerDesc": "Menor calidad, mejor compresión",
  "presetSmallest": "Más pequeño",
  "presetSmallestDesc": "Calidad mínima, compresión máxima",
  "compressionRasterNote": "La compresión utiliza rasterización (imágenes). Es posible que ya no se puedan seleccionar texto/vectores.",
  "compressionFailed": "Error de compresión",
  "compressionLevel": "Nivel de compresión",
  "mergeFileCountSize": "{count} archivo(s) - {size} MB total",
  "addMore": "Agregar más",
  "moveUp": "Subir",
  "moveDown": "Bajar",
  "remove": "Quitar",
  "back": "Atrás",
  "redactMode": "Redactar",
  "selectMode": "Seleccione",
  "clearPage": "Borrar página",
  "outputQuality": "Calidad de salida",
  "prev": "Anterior",
  "next": "Siguiente",
  "pageOfShort": "Página {current} / {total}",
  "redactionRasterNote": "La exportación de redacción rasteriza las páginas para eliminar permanentemente el texto/vectores subyacentes.",
  "dropPdfToOrganize": "Coloque un PDF aquí para organizar páginas",
  "organizePagesTitle": "Organizar páginas",
  "selectAll": "Seleccionar todo",
  "selectedCount": "{count} seleccionado",
  "rotateLeft": "Girar a la izquierda",
  "rotateLeftLabel": "Girar ⟲",
  "rotateRight": "Girar a la derecha",
  "rotateRightLabel": "Girar ⟳",
  "deleteSelectedPages": "Eliminar páginas seleccionadas",
  "delete": "Eliminar",
  "exportSelected": "Exportar seleccionado",
  "select": "Seleccione",
  "pageShort": "p{count}",
  "rotate": "Girar",
  "loadPdfFailed": "No se pudo cargar PDF",
  "noPagesSelected": "No hay páginas seleccionadas.",
  "exportFailed": "Exportación fallida",
  "dropPdfToDeletePages": "Coloque un PDF aquí para eliminar páginas",
  "deletePagesTitle": "Eliminar páginas",
  "markedForDeletion": "{count} marcadas para eliminación",
  "exit": "Salir",
  "pagesRangeOfTotal": "Páginas {start}-{end} de {total}",
  "pdfNotLoaded": "PDF no cargadas.",
  "deleteAllPagesError": "No puede eliminar todas las páginas.",
  "deletePageKeepHint": "Haga clic para mantener esta página",
  "deletePageRemoveHint": "Haga clic para eliminar esta página",
  "pageLabel": "Página {count}",
  "cropFailed": "Cosecha fallida",
  "leftPt": "Izquierda (pt)",
  "rightPt": "Derecha (pt)",
  "topPt": "Arriba (pt)",
  "bottomPt": "Abajo (pt)",
  "watermarkDefaultText": "CONFIDENCIAL",
  "watermarkFallbackText": "MARCA DE AGUA",
  "watermarkTextPlaceholder": "Ingrese el texto de la marca de agua...",
  "opacityLabel": "Opacidad",
  "fontSizeLabel": "Tamaño de fuente",
  "rotationLabel": "Rotación",
  "watermarkFailed": "No se pudo agregar la marca de agua",
  "annotationClickToEdit": "Haga clic para editar",
  "toolSelect": "Seleccione",
  "toolText": "Texto",
  "toolEditText": "Editar texto",
  "toolAddText": "Agregar texto",
  "toolHighlight": "Resalte",
  "toolDraw": "Dibuje",
  "toolRectangle": "Rectángulo",
  "toolCircle": "Círculo",
  "toolArrow": "Flecha",
  "toolLine": "Línea",
  "toolEraser": "Borrador",
  "colorLabel": "Color",
  "strokeColorLabel": "Color del trazo",
  "strokeWidthLabel": "Ancho del trazo",
  "undo": "Deshacer",
  "redo": "Rehacer",
  "clearAll": "Borrar todo",
  "loadPdfFailedTryAgain": "No se pudo cargar PDF. Por favor inténtalo de nuevo.",
  "noPdfSelected": "No hay ningún archivo PDF seleccionado",
  "uploadProgressLabel": "Progreso de la carga",
  "loadingPleaseWait": "Cargando, por favor espere...",
  "productivityTip": "Consejo de productividad",
  "cancel": "Cancelar",
  "uploadTipPreparing": "Cargando y preparando su documento. Optimizando para editar...",
  "uploadTipEditor": "Preparando el editor. Por lo general, esto lleva sólo un momento.",
  "uploadTipLarge": "Consejo: Los archivos PDF más grandes pueden tardar un poco más en cargarse; gracias por su paciencia.",
  "pdfPasswordProtected": "Este PDF está protegido con contraseña. Desbloqueelo primero y luego vuelva a abrirlo en el editor.",
  "pdfExportFailed": "Algo salió mal al exportar tu PDF. Por favor inténtalo de nuevo.",
  "convertOpenFailed": "No se pudo abrir la herramienta Convertir. Por favor inténtalo de nuevo.",
  "statusWorking": "Trabajando...",
  "statusReady": "Listo",
  "statusCanceled": "Cancelado",
  "statusWaiting": "Esperando...",
  "statusLoading": "Cargando...",
  "uploadNew": "Cargar nuevo",
  "saveDownload": "Guardar y descargar",
  "pdfEditorTitle": "PDF Editor",
  "toolLabel": "Herramienta",
  "annotationsOnPages": "Anotaciones en {count} página(s)",
  "dropPdfsToMerge": "Colocar archivos PDF aquí para fusionarlos",
  "reset": "Restablecer",
  "convert": "Convertir",
  "dropFilesToConvert": "Colocar archivos aquí para convertir",
  "convertSubtitle": "PDF → imágenes/texto, imágenes → PDF u Office → PDF (hospedado propio)",
  "convertDownload": "Convertir y descargar",
  "exportPdf": "Exportar PDF",
  "dropPdfToRedact": "Coloque un PDF aquí para redactar",
  "redactSubtitle": "Eliminar permanentemente información confidencial",
  "redactionFailed": "Error en la redacción",
  "exporting": "Exportando...",
  "exportRedacted": "Exportar redactado PDF",
  "applyingWatermark": "Aplicando marca de agua...",
  "pageOf": "Página {current} de {total}",
  "zoomIn": "Acercar",
  "zoomOut": "Alejar",
  "signInSubtitle": "Continúe con Google para desbloquear un mayor uso gratuito. El inicio de sesión",
  "googleNotConfigured": "Google no está configurado en este entorno.",
  "preferNotToSignIn": "¿Prefieres no iniciar sesión?",
  "continueAsGuest": "Continuar como invitado",
  "passwordReset": "Restablecer contraseña",
  "passwordResetUnavailable": "El restablecimiento de contraseña no está disponible porque esta aplicación solo admite Google inicio de sesión con un clic.",
  "backToSignIn": "Volver al inicio de sesión",
  "contactSendFailed": "No se pudo enviar",
  "contactSendSuccess": "¡Gracias! Recibimos su mensaje y nos comunicaremos con usted pronto.",
  "contactSendError": "Algo salió mal. Por favor inténtalo de nuevo.",
  "fullNamePlaceholder": "John Newman",
  "emailPlaceholder": "ejemplo@mail.com",
  "descriptionPlaceholder": "Por favor ingrese los detalles de su solicitud. Un miembro de nuestro personal de soporte le responderá lo antes posible.",
  "subjectGeneral": "Consulta general",
  "subjectSupport": "Soporte técnico",
  "subjectBilling": "Pregunta sobre facturación",
  "subjectFeature": "Solicitud de función",
  "subjectBug": "Informe de error",
  "subjectPartnership": "Asociación",
  "subjectOther": "Otro",
  "contactFaqGeneral1Q": "¿Qué es QwerPDF?",
  "contactFaqGeneral1A": "QwerPDF es un editor PDF en línea todo en uno que le permite editar, convertir, firmar y administrar sus documentos PDF de manera fácil y segura.",
  "contactFaqGeneral2Q": "¿Necesito descargar o instalar algo para usar QwerPDF?",
  "contactFaqGeneral2A": "No, QwerPDF está completamente basado en web.",
  "contactFaqGeneral3Q": "¿Puedo fusionar archivos PDF con QwerPDF?",
  "contactFaqGeneral3A": "Sí, puedes combinar fácilmente varios archivos PDF en un solo documento.",
  "contactFaqGeneral4Q": "¿Puedo convertir un documento de Word en un PDF?",
  "contactFaqGeneral4A": "Sí. Nuestra herramienta Convertir actualmente admite PDF ↔ imágenes/texto e imágenes → PDF. Office-to-PDF se puede agregar mediante un servicio de conversión de backend.",
  "contactFaqSecurity1Q": "¿Es seguro usar QwerPDF?",
  "contactFaqSecurity1A": "QwerPDF ejecuta las operaciones principales de PDF localmente en su navegador para muchas herramientas, por lo que sus archivos no necesitan salir de su dispositivo para realizar ediciones, conversión y compresión básicas.",
  "contactFaqSecurity2Q": "¿Guardan mis documentos?",
  "contactFaqSecurity2A": "Esta aplicación de demostración no almacena sus documentos en el servidor a menos que los cargue explícitamente en un servicio externo.",
  "contactFaqBilling1Q": "¿Cómo puedo cancelar mi suscripción?",
  "contactFaqBilling1A": "Puede cancelar su suscripción desde la configuración de su cuenta.",
  "plansAndPricingLeft": "Planes",
  "plansAndPricingRight": "Precios",
  "processing": "Procesando...",
  "sending": "Enviando...",
  "signInToSubscribe": "Inicie sesión para suscribirse",
  "checkoutCreateFailed": "No se puede crear una sesión de pago. Por favor inténtalo de nuevo.",
  "checkoutError": "Ocurrió un error. Por favor inténtalo de nuevo.",
  "new": "nuevo",
  "planFeatureEditor": "Potente PDF Editor",
  "planFeatureSignatures": "Firmas digitales",
  "planFeatureWorkspace": "Espacio de trabajo",
  "planFeatureWorkspaceSubtitle": "con administrador de archivos",
  "planFeatureConversion": "Conversión ilimitada de archivos",
  "planFeatureRedaction": "Herramienta de redacción",
  "planFeatureIntegrations": "Drive, OneDrive",
  "planFeatureIntegrationsSubtitle": "e integración de DropBox",
  "planFeatureOcr": "OCR tecnología",
  "planFeatureManipulation": "Manipulación de páginas",
  "planFeatureNoSoftware": "Sin software",
  "planFeatureNoSoftwareSubtitle": "Se requiere instalación",
  "planFeatureSecurity": "Múltiples herramientas de seguridad",
  "planFeatureSso": "SSO Iniciar sesión",
  "planFeatureUpcoming": "Acceso a todas las próximas funciones",
  "planFeatureUpcomingSubtitle": "",
  "questionsAndAnswers": "Preguntas y respuestas",
  "planFaq1Q": "¿Cuáles son mis opciones de pago?",
  "planFaq1A": "Aceptamos todas las principales tarjetas de crédito, PayPal y otros métodos de pago según su región.",
  "planFaq2Q": "¿Por qué ciertos sitios web ofrecen PDF funciones de edición de forma gratuita?",
  "planFaq2A": "Algunos sitios web ofrecen funciones gratuitas limitadas, pero pueden tener restricciones en cuanto al tamaño del archivo, la cantidad de documentos o incluir marcas de agua.",
  "planFaq3Q": "¿Es seguro usar QwerPDF?",
  "planFaq3A": "Sí, QwerPDF utiliza cifrado y medidas de seguridad estándar de la industria para proteger sus documentos e información personal.",
  "planFaq4Q": "¿Puedo cambiar mi plan?",
  "planFaq4A": "Sí, puede actualizar o degradar su plan en cualquier momento desde la configuración de su cuenta.",
  "planFaq5Q": "¿Qué pasará si cancelo mi suscripción?",
  "planFaq5A": "Continuarás teniendo acceso a funciones premium hasta el final de tu período de facturación.",
  "planFaq6Q": "¿Cómo puedo cancelar mi suscripción?",
  "planFaq6A": "Puede cancelar su suscripción desde la configuración de su cuenta en la sección Suscripción.",
  "planFaq7Q": "¿Mi suscripción se renovará automáticamente?",
  "planFaq7A": "Sí, las suscripciones se renuevan automáticamente a menos que las cancele antes de la fecha de renovación.",
  "paymentSuccessTitle": "¡Pago exitoso!",
  "paymentSuccessDesc": "Gracias por suscribirte a QwerPDF Premium. Ahora tiene acceso ilimitado a todas nuestras herramientas PDF.",
  "startEditing": "Comenzar a editar archivos PDF",
  "viewSubscription": "Ver suscripción",
  "unsubscribeTitle": "Cómo cancelar su suscripción QwerPDF",
  "unsubscribeIntro1": "¡Gracias por visitar QwerPDF.com! Realmente valoramos su negocio y apreciamos tenerlo como nuestro cliente.",
  "unsubscribeIntro2": "Para comenzar, simplemente siga estos tres sencillos pasos:",
  "unsubscribeStep1Title": "1. Inicie sesión en su cuenta QwerPDF",
  "clickHere": "Haga clic aquí",
  "unsubscribeStep1Desc": "para acceder a la página de inicio de sesión.",
  "unsubscribeStep2Title": "2. Una vez que haya iniciado sesión en su panel de control, acceda a la configuración en la esquina superior derecha de su pantalla.",
  "unsubscribeStep2Desc": "Desde tu configuración, haz clic en \"Suscripción\". Esto lo llevará a la página correspondiente para cancelar su cuenta.",
  "unsubscribeStep3Title": "3. Haga clic en «Cancelar Plan»",
  "unsubscribeStep3Desc": "Siga todos los pasos para cancelar su cuenta.",
  "unsubscribeHelpTitle": "¿Tiene dificultades para iniciar sesión en su cuenta?",
  "unsubscribeHelpDesc1": "Si tiene algún problema para iniciar sesión, intente iniciar sesión con Google nuevamente.",
  "unsubscribeHelpDesc2Prefix": "Si aún tiene problemas,",
  "unsubscribeHelpDesc2Suffix": "para confirmar que su cuenta aún está activa.",
  "faqGeneral1Q": "¿Qué es QwerPDF?",
  "faqGeneral1A": "QwerPDF es un editor PDF en línea todo en uno que le permite editar, convertir, firmar y administrar sus documentos PDF de manera fácil y segura.",
  "faqGeneral2Q": "¿Necesito descargar o instalar algo para usar QwerPDF?",
  "faqGeneral2A": "No, QwerPDF está completamente basado en web. Puede utilizar todas nuestras herramientas directamente en su navegador sin descargar ningún software.",
  "faqGeneral3Q": "¿Puedo fusionar archivos PDF con QwerPDF?",
  "faqGeneral3A": "Sí, puede combinar fácilmente varios archivos PDF en un solo documento utilizando nuestra herramienta Combinar documentos.",
  "faqGeneral4Q": "¿Puedo convertir un documento de Word en un PDF?",
  "faqGeneral4A": "¡Absolutamente! QwerPDF admite la conversión de varios formatos de archivos, incluidos Word, Excel, PowerPoint e imágenes, a PDF.",
  "faqGeneral5Q": "¿Cómo agrego, muevo y giro páginas?",
  "faqGeneral5A": "Utilice nuestra herramienta Organizar páginas para agregar, mover, eliminar o rotar páginas en sus documentos PDF.",
  "faqGeneral6Q": "¿Por qué ciertos sitios web ofrecen PDF funciones de edición de forma gratuita?",
  "faqGeneral6A": "Algunos sitios web ofrecen funciones gratuitas limitadas, pero pueden tener restricciones en cuanto al tamaño del archivo, la cantidad de documentos o incluir marcas de agua. QwerPDF proporciona herramientas premium con todas las funciones y sin limitaciones.",
  "faqSecurity1Q": "¿Es seguro usar QwerPDF?",
  "faqSecurity1A": "Sí, QwerPDF utiliza cifrado y medidas de seguridad estándar de la industria para proteger sus documentos e información personal.",
  "faqSecurity2Q": "¿Dónde guarda QwerPDF mis documentos?",
  "faqSecurity2A": "Sus documentos se almacenan en servidores seguros en la nube con cifrado. Los archivos se eliminan automáticamente después del procesamiento, a menos que elija guardarlos en su cuenta.",
  "faqSecurity3Q": "¿QwerPDF admite el inicio de sesión único?",
  "faqSecurity3A": "Sí, admitimos SSO (inicio de sesión único) para clientes empresariales a través de varios proveedores de identidad.",
  "faqSecurity4Q": "¿Cómo protejo con contraseña un PDF?",
  "faqSecurity4A": "Cargue su PDF a QwerPDF, seleccione la herramienta Protección con contraseña, establezca la contraseña que desee y descargue el archivo seguro.",
  "faqBilling1Q": "¿Mi suscripción se renovará automáticamente?",
  "faqBilling1A": "Sí, las suscripciones se renuevan automáticamente a menos que las cancele antes de la fecha de renovación.",
  "faqBilling2Q": "¿Cómo puedo cancelar mi suscripción?",
  "faqBilling2A": "Puede cancelar su suscripción desde la configuración de su cuenta en la sección Suscripción.",
  "faqBilling3Q": "¿Qué pasará si cancelo mi suscripción?",
  "faqBilling3A": "Continuarás teniendo acceso a funciones premium hasta el final de tu período de facturación. Después de eso, su cuenta volverá a tener funciones gratuitas.",
  "faqBilling4Q": "¿A qué me da acceso la prueba paga?",
  "faqBilling4A": "La prueba paga le brinda acceso completo a todas las funciones premium por un tiempo limitado.",
  "faqBilling5Q": "¿Puedo cambiar mi plan?",
  "faqBilling5A": "Sí, puede actualizar o degradar su plan en cualquier momento desde la configuración de su cuenta.",
  "faqBilling6Q": "¿Cuáles son mis opciones de pago?",
  "faqBilling6A": "Aceptamos todas las principales tarjetas de crédito, PayPal y otros métodos de pago según su región."
}
